{
  "_id": {
    "$oid": "66d3a1b5b0209cf380a25719"
  },
  "name": "אימון C",
  "description": "פלג גוף תחתון",
  "exercises": [
    {
      "_id": {
        "$oid": "66d3a1b5b0209cf380a2571a"
      },
      "name": "סקוואט בסמית",
      "sets": 3,
      "reps": 8,
      "muscleGroup": "רגליים",
      "done": true,
      "lastdoneDate": {
        "$date": "2024-07-29T00:00:00Z"
      },
      "lastWeight": 5,
      "lastReps": 8,
      "lastSets": 3,
      "lastDifficulty": 8,
      "notes": "",
      "weightHistory": [
        {
          "_id": {
            "$oid": "66d3a1b5b0209cf380a2571b"
          },
          "weight": 5,
          "date": {
            "$date": "2024-07-29T00:00:00Z"
          }
        }
      ],
      "repsHistory": [
        {
          "_id": {
            "$oid": "66d3a1b5b0209cf380a2571c"
          },
          "reps": 8,
          "date": {
            "$date": "2024-07-29T00:00:00Z"
          }
        }
      ],
      "setsHistory": [
        {
          "_id": {
            "$oid": "66d3a1b5b0209cf380a2571d"
          },
          "sets": 3,
          "date": {
            "$date": "2024-07-29T00:00:00Z"
          }
        }
      ],
      "difficultyHistory": [
        {
          "_id": {
            "$oid": "66d3a1b5b0209cf380a2571e"
          },
          "difficulty": 8,
          "date": {
            "$date": "2024-07-29T00:00:00Z"
          }
        }
      ],
      "scoreHistory": [
        {
          "_id": {
            "$oid": "66d3a1b5b0209cf380a2571f"
          },
          "score": 5,
          "date": {
            "$date": "2024-07-29T00:00:00Z"
          }
        }
      ]
    }
  ],
  "numberOfExercises": 1,
  "completionRate": 0,
  "startDate": {
    "$date": "2024-07-01T00:00:00Z"
  },
  "lastDate": {
    "$date": "2024-07-29T00:00:00Z"
  },
  "status": "In Progress",
  "generalNotes": "",
  "user": {
    "$oid": "66d39f954f541e06cabf0c79"
  },
  "duration": null
}